pysimplex-1.5.0.dist-info/RECORD
pysimplex-1.5.0.dist-info/WHEEL
pysimplex-1.5.0.dist-info/top_level.txt
pysimplex-1.5.0.dist-info/METADATA
pysimplex/__init__.py
pysimplex/_simplex.cpython-312-darwin.so
