Metadata-Version: 2.1
Name: pysimplex
Version: 1.5.0
Summary: A fast Clifford circuit simulator
Home-page: https://github.com/CQCL/simplex
Author: Alec Edgington
Author-email: alec.edgington@cambridgequantum.com
License: Apache 2
Classifier: Environment :: Console
Classifier: Programming Language :: Python :: 3.10
Classifier: Programming Language :: Python :: 3.11
Classifier: Programming Language :: Python :: 3.12
Classifier: License :: OSI Approved :: Apache Software License
Classifier: Operating System :: POSIX :: Linux
Classifier: Operating System :: MacOS :: MacOS X
Classifier: Operating System :: Microsoft :: Windows
Classifier: Intended Audience :: Developers
Classifier: Intended Audience :: Science/Research
Classifier: Topic :: Scientific/Engineering
Requires-Python: >=3.10
